[
  {
    "symbol": "^GVZ",
    "name": "CBOE Gold Volatitity Index",
    "price": 17.54,
    "changesPercentage": -4.21,
    "change": -0.77,
    "dayLow": 0,
    "dayHigh": 0,
    "yearHigh": 54.37,
    "yearLow": 0,
    "marketCap": null,
    "priceAvg50": 21.492222,
    "priceAvg200": 21.511295,
    "volume": 0,
    "avgVolume": 0,
    "exchange": "INDEX",
    "open": 0,
    "previousClose": 18.31,
    "eps": null,
    "pe": null,
    "earningsAnnouncement": null,
    "sharesOutstanding": null,
    "timestamp": 1605697056
  },
  {
    "symbol": "^NZ50",
    "name": "S&P/NZX 50 INDEX GROSS",
    "price": 12605.96,
    "changesPercentage": -1.25,
    "change": -159.07,
    "dayLow": 12584.84,
    "dayHigh": 12831.33,
    "yearHigh": 12831.33,
    "yearLow": 8209.04,
    "marketCap": null,
    "priceAvg50": 12301.048,
    "priceAvg200": 11641.086,
    "volume": 0,
    "avgVolume": 31632592,
    "exchange": "INDEX",
    "open": 12765.03,
    "previousClose": 12765.03,
    "eps": null,
    "pe": null,
    "earningsAnnouncement": null,
    "sharesOutstanding": null,
    "timestamp": 1605697056
  },
  {
    "symbol": "^RUATR",
    "name": "Russell 3000 Total Return",
    "price": 11598.362,
    "changesPercentage": -0.24,
    "change": -27.979,
    "dayLow": 11515.564,
    "dayHigh": 11638.759,
    "yearHigh": 11638.759,
    "yearLow": 11515.564,
    "marketCap": null,
    "priceAvg50": null,
    "priceAvg200": null,
    "volume": 0,
    "avgVolume": null,
    "exchange": "INDEX",
    "open": 11623.718,
    "previousClose": 11626.341,
    "eps": null,
    "pe": null,
    "earningsAnnouncement": null,
    "sharesOutstanding": null,
    "timestamp": 1605697056
  },
  {
    "symbol": "^SSEC",
    "name": "Shanghai Stock Exchange Composite Index",
    "price": 3328.1028,
    "changesPercentage": 0.47,
    "change": 15.4358,
    "dayLow": 3293.766,
    "dayHigh": 3328.1028,
    "yearHigh": 3331.915,
    "yearLow": 3271.461,
    "marketCap": null,
    "priceAvg50": 3331.522,
    "priceAvg200": 3331.522,
    "volume": 3623574312,
    "avgVolume": 205800,
    "exchange": "INDEX",
    "open": 3307.15,
    "previousClose": 3312.667,
    "eps": null,
    "pe": null,
    "earningsAnnouncement": null,
    "sharesOutstanding": null,
    "timestamp": 1605697056
  },
  {
    "symbol": "^N100",
    "name": "EURONEXT 100",
    "price": 1084.24,
    "changesPercentage": 0.3,
    "change": 3.26,
    "dayLow": 1075.9,
    "dayHigh": 1084.36,
    "yearHigh": 1182.1,
    "yearLow": 710.47,
    "marketCap": null,
    "priceAvg50": 992.88806,
    "priceAvg200": 973.52325,
    "volume": 0,
    "avgVolume": 242086151,
    "exchange": "INDEX",
    "open": 1077.06,
    "previousClose": 1080.98,
    "eps": null,
    "pe": null,
    "earningsAnnouncement": null,
    "sharesOutstanding": null,
    "timestamp": 1605697056
  },
  {
    "symbol": "^NYA",
    "name": "NYSE COMPOSITE (DJ)",
    "price": 13949.098,
    "changesPercentage": -0.24,
    "change": -33.089,
    "dayLow": 0,
    "dayHigh": 0,
    "yearHigh": 14183.26,
    "yearLow": 0,
    "marketCap": null,
    "priceAvg50": 13107.319,
    "priceAvg200": 12493.101,
    "volume": 0,
    "avgVolume": 4338874615,
    "exchange": "INDEX",
    "open": 0,
    "previousClose": 13982.187,
    "eps": null,
    "pe": null,
    "earningsAnnouncement": null,
    "sharesOutstanding": null,
    "timestamp": 1605697056
  },
  {
    "symbol": "^FCHI",
    "name": "CAC 40",
    "price": 5499.71,
    "changesPercentage": 0.3,
    "change": 16.71,
    "dayLow": 5452.12,
    "dayHigh": 5502.28,
    "yearHigh": 6111.41,
    "yearLow": 3632.06,
    "marketCap": null,
    "priceAvg50": 4957.367,
    "priceAvg200": 4898.571,
    "volume": 0,
    "avgVolume": 61862054,
    "exchange": "INDEX",
    "open": 5468.17,
    "previousClose": 5483,
    "eps": null,
    "pe": null,
    "earningsAnnouncement": null,
    "sharesOutstanding": null,
    "timestamp": 1605697056
  },
  {
    "symbol": "^IBEX",
    "name": "IBEX 35",
    "price": 7943.6,
    "changesPercentage": 0.12,
    "change": 9.3,
    "dayLow": 7888.7,
    "dayHigh": 7970.6,
    "yearHigh": 10100.2,
    "yearLow": 5814.5,
    "marketCap": null,
    "priceAvg50": 6981.5723,
    "priceAvg200": 7084.186,
    "volume": 94782348,
    "avgVolume": 266652671,
    "exchange": "INDEX",
    "open": 7914.1,
    "previousClose": 7934.3,
    "eps": null,
    "pe": null,
    "earningsAnnouncement": null,
    "sharesOutstanding": null,
    "timestamp": 1605697056
  },
  {
    "symbol": "^IXIC",
    "name": "NASDAQ Composite",
    "price": 11899.343,
    "changesPercentage": -0.21,
    "change": -24.757,
    "dayLow": 11852.41,
    "dayHigh": 11950.183,
    "yearHigh": 12108.07,
    "yearLow": 6631.42,
    "marketCap": null,
    "priceAvg50": 11492.763,
    "priceAvg200": 10653.177,
    "volume": 3803457498,
    "avgVolume": 3748333230,
    "exchange": "INDEX",
    "open": 11913.3,
    "previousClose": 11924.1,
    "eps": null,
    "pe": null,
    "earningsAnnouncement": null,
    "sharesOutstanding": null,
    "timestamp": 1605697056
  },
  {
    "symbol": "^KS11",
    "name": "KOSPI Composite Index",
    "price": 2545.64,
    "changesPercentage": 0.26,
    "change": 6.49,
    "dayLow": 2536.78,
    "dayHigh": 2553.95,
    "yearHigh": 2556.09,
    "yearLow": 1439.43,
    "marketCap": null,
    "priceAvg50": 2387.3481,
    "priceAvg200": 2247.6104,
    "volume": 923504,
    "avgVolume": 933562,
    "exchange": "INDEX",
    "open": 2548.85,
    "previousClose": 2539.15,
    "eps": null,
    "pe": null,
    "earningsAnnouncement": null,
    "sharesOutstanding": null,
    "timestamp": 1605697056
  },
  {
    "symbol": "^HSI",
    "name": "HANG SENG INDEX",
    "price": 26544.29,
    "changesPercentage": 0.49,
    "change": 129.2,
    "dayLow": 26344.86,
    "dayHigh": 26618.01,
    "yearHigh": 29174.92,
    "yearLow": 21139.26,
    "marketCap": null,
    "priceAvg50": 24826.094,
    "priceAvg200": 24671.86,
    "volume": 0,
    "avgVolume": 2012088139,
    "exchange": "INDEX",
    "open": 26434.24,
    "previousClose": 26415.09,
    "eps": null,
    "pe": null,
    "earningsAnnouncement": null,
    "sharesOutstanding": null,
    "timestamp": 1605697056
  },
  {
    "symbol": "^N225",
    "name": "Nikkei 225",
    "price": 25728.14,
    "changesPercentage": -1.1,
    "change": -286.48,
    "dayLow": 25656.7,
    "dayHigh": 25882.14,
    "yearHigh": 26057.3,
    "yearLow": 16358.19,
    "marketCap": null,
    "priceAvg50": 23885.723,
    "priceAvg200": 22792.742,
    "volume": 0,
    "avgVolume": 64161,
    "exchange": "INDEX",
    "open": 25860.55,
    "previousClose": 26014.62,
    "eps": null,
    "pe": null,
    "earningsAnnouncement": null,
    "sharesOutstanding": null,
    "timestamp": 1605697056
  },
  {
    "symbol": "^TWII",
    "name": "TSEC weighted index",
    "price": 13773.29,
    "changesPercentage": 1.33,
    "change": 180.28,
    "dayLow": 13608.72,
    "dayHigh": 13773.29,
    "yearHigh": 13780.12,
    "yearLow": 8523.63,
    "marketCap": null,
    "priceAvg50": 12900.597,
    "priceAvg200": 12233.083,
    "volume": 0,
    "avgVolume": 3815195,
    "exchange": "INDEX",
    "open": 13628.42,
    "previousClose": 13593.01,
    "eps": null,
    "pe": null,
    "earningsAnnouncement": null,
    "sharesOutstanding": null,
    "timestamp": 1605697056
  },
  {
    "symbol": "^OVX",
    "name": "CBOE Crude Oil Volatility Index ",
    "price": 45.08,
    "changesPercentage": -3.86,
    "change": -1.81,
    "dayLow": 0,
    "dayHigh": 0,
    "yearHigh": 517.19,
    "yearLow": 0,
    "marketCap": null,
    "priceAvg50": 50.025555,
    "priceAvg200": 53.432014,
    "volume": 0,
    "avgVolume": 0,
    "exchange": "INDEX",
    "open": 0,
    "previousClose": 46.89,
    "eps": null,
    "pe": null,
    "earningsAnnouncement": null,
    "sharesOutstanding": null,
    "timestamp": 1605697056
  },
  {
    "symbol": "^VVIX",
    "name": "CBOE VIX VOLATILITY INDEX",
    "price": 116.25,
    "changesPercentage": 1.09,
    "change": 1.25,
    "dayLow": 0,
    "dayHigh": 0,
    "yearHigh": 209.76,
    "yearLow": 0,
    "marketCap": null,
    "priceAvg50": 118.30444,
    "priceAvg200": 117.25108,
    "volume": 0,
    "avgVolume": 0,
    "exchange": "INDEX",
    "open": 0,
    "previousClose": 115,
    "eps": null,
    "pe": null,
    "earningsAnnouncement": null,
    "sharesOutstanding": null,
    "timestamp": 1605697056
  },
  {
    "symbol": "^IRX",
    "name": "13 Week Treasury Bill",
    "price": 0.08,
    "changesPercentage": 0,
    "change": 0,
    "dayLow": 0.08,
    "dayHigh": 0.08,
    "yearHigh": 3.39,
    "yearLow": -0.235,
    "marketCap": null,
    "priceAvg50": 0.087,
    "priceAvg200": 0.10546762,
    "volume": null,
    "avgVolume": 0,
    "exchange": "INDEX",
    "open": 0,
    "previousClose": 0.08,
    "eps": null,
    "pe": null,
    "earningsAnnouncement": null,
    "sharesOutstanding": null,
    "timestamp": 1605697056
  },
  {
    "symbol": "^TA125.TA",
    "name": "TA-125",
    "price": 1483.4,
    "changesPercentage": 0.7,
    "change": 10.25,
    "dayLow": 1474.25,
    "dayHigh": 1483.71,
    "yearHigh": 1684.78,
    "yearLow": 1076.65,
    "marketCap": null,
    "priceAvg50": 1404.6431,
    "priceAvg200": 1395.4606,
    "volume": 0,
    "avgVolume": 77952175,
    "exchange": "INDEX",
    "open": 1475.59,
    "previousClose": 1473.15,
    "eps": null,
    "pe": null,
    "earningsAnnouncement": null,
    "sharesOutstanding": null,
    "timestamp": 1605697056
  },
  {
    "symbol": "^KLSE",
    "name": "FTSE Bursa Malaysia KLCI",
    "price": 1604.75,
    "changesPercentage": -0.34,
    "change": -5.4,
    "dayLow": 1595.09,
    "dayHigh": 1611.58,
    "yearHigh": 1618.01,
    "yearLow": 1207.8,
    "marketCap": null,
    "priceAvg50": 1514.3212,
    "priceAvg200": 1522.1646,
    "volume": 0,
    "avgVolume": 169731388,
    "exchange": "INDEX",
    "open": 1611.08,
    "previousClose": 1610.15,
    "eps": null,
    "pe": null,
    "earningsAnnouncement": null,
    "sharesOutstanding": null,
    "timestamp": 1605697056
  },
  {
    "symbol": "^MID",
    "name": "S&P MID CAP 400 INDEX",
    "price": 2159.63,
    "changesPercentage": 0.19,
    "change": 4.08,
    "dayLow": 0,
    "dayHigh": 0,
    "yearHigh": 2166.98,
    "yearLow": 0,
    "marketCap": null,
    "priceAvg50": 1990.6927,
    "priceAvg200": 1863.5488,
    "volume": 0,
    "avgVolume": 0,
    "exchange": "INDEX",
    "open": 0,
    "previousClose": 2155.55,
    "eps": null,
    "pe": null,
    "earningsAnnouncement": null,
    "sharesOutstanding": null,
    "timestamp": 1605697056
  },
  {
    "symbol": "^RMCCTR",
    "name": "Russell Midcap Total Return",
    "price": 17843.197,
    "changesPercentage": 1.59,
    "change": 278.453,
    "dayLow": 17843.197,
    "dayHigh": 17843.197,
    "yearHigh": 17843.197,
    "yearLow": 17843.197,
    "marketCap": null,
    "priceAvg50": null,
    "priceAvg200": null,
    "volume": 0,
    "avgVolume": null,
    "exchange": "INDEX",
    "open": 17843.197,
    "previousClose": 17564.744,
    "eps": null,
    "pe": null,
    "earningsAnnouncement": null,
    "sharesOutstanding": null,
    "timestamp": 1605697056
  },
  {
    "symbol": "^AXJO",
    "name": "S&P/ASX 200",
    "price": 6531.1,
    "changesPercentage": 0.51,
    "change": 32.9,
    "dayLow": 6494.7,
    "dayHigh": 6541.2,
    "yearHigh": 7197.2,
    "yearLow": 4402.5,
    "marketCap": null,
    "priceAvg50": 6135.3887,
    "priceAvg200": 5959.6865,
    "volume": 0,
    "avgVolume": 728022,
    "exchange": "INDEX",
    "open": 6498.2,
    "previousClose": 6498.2,
    "eps": null,
    "pe": null,
    "earningsAnnouncement": null,
    "sharesOutstanding": null,
    "timestamp": 1605697056
  },
  {
    "symbol": "^RUITR",
    "name": "Russell 1000 Total Return",
    "price": 11901.365,
    "changesPercentage": -0.28,
    "change": -33.464,
    "dayLow": 11826.389,
    "dayHigh": 11943.858,
    "yearHigh": 11943.858,
    "yearLow": 11826.389,
    "marketCap": null,
    "priceAvg50": null,
    "priceAvg200": null,
    "volume": 0,
    "avgVolume": null,
    "exchange": "INDEX",
    "open": 11932.969,
    "previousClose": 11934.829,
    "eps": null,
    "pe": null,
    "earningsAnnouncement": null,
    "sharesOutstanding": null,
    "timestamp": 1605697056
  },
  {
    "symbol": "000001.SS",
    "name": "SSE Composite Index",
    "price": 3347.3035,
    "changesPercentage": 0.22,
    "change": 7.4085,
    "dayLow": 3333.9917,
    "dayHigh": 3358.8938,
    "yearHigh": 3458.791,
    "yearLow": 2646.805,
    "marketCap": null,
    "priceAvg50": 3301.6555,
    "priceAvg200": 3195.3008,
    "volume": 2983322124,
    "avgVolume": 232176,
    "exchange": "INDEX",
    "open": 3337.3315,
    "previousClose": 3339.895,
    "eps": null,
    "pe": null,
    "earningsAnnouncement": null,
    "sharesOutstanding": null,
    "timestamp": 1605697056
  },
  {
    "symbol": "^VXSLV",
    "name": "CBOE SILVER ETF VOLATILITY INDE",
    "price": 41.37,
    "changesPercentage": -1.71,
    "change": -0.72,
    "dayLow": 0,
    "dayHigh": 0,
    "yearHigh": 0,
    "yearLow": 0,
    "marketCap": null,
    "priceAvg50": null,
    "priceAvg200": null,
    "volume": 0,
    "avgVolume": null,
    "exchange": "INDEX",
    "open": 0,
    "previousClose": 42.09,
    "eps": null,
    "pe": null,
    "earningsAnnouncement": null,
    "sharesOutstanding": null,
    "timestamp": 1605697056
  },
  {
    "symbol": "^FTSE",
    "name": "FTSE 100",
    "price": 6358.7,
    "changesPercentage": -0.1,
    "change": -6.63,
    "dayLow": 6326.74,
    "dayHigh": 6365.33,
    "yearHigh": 7689.7,
    "yearLow": 4898.8,
    "marketCap": null,
    "priceAvg50": 5942.9194,
    "priceAvg200": 6049.0747,
    "volume": 0,
    "avgVolume": 793598118,
    "exchange": "INDEX",
    "open": 6365.33,
    "previousClose": 6365.33,
    "eps": null,
    "pe": null,
    "earningsAnnouncement": null,
    "sharesOutstanding": null,
    "timestamp": 1605697056
  },
  {
    "symbol": "^GDAXI",
    "name": "DAX PERFORMANCE-INDEX",
    "price": 13166.38,
    "changesPercentage": 0.25,
    "change": 32.91,
    "dayLow": 13074.67,
    "dayHigh": 13182.32,
    "yearHigh": 13795.24,
    "yearLow": 8255.65,
    "marketCap": null,
    "priceAvg50": 12666.149,
    "priceAvg200": 12458.841,
    "volume": 0,
    "avgVolume": 74742175,
    "exchange": "INDEX",
    "open": 13086.43,
    "previousClose": 13133.47,
    "eps": null,
    "pe": null,
    "earningsAnnouncement": null,
    "sharesOutstanding": null,
    "timestamp": 1605697056
  },
  {
    "symbol": "^XNDX",
    "name": "NASDAQ 100 Total Return Index",
    "price": 13994.143,
    "changesPercentage": -0.3,
    "change": -41.957,
    "dayLow": 13978.618,
    "dayHigh": 14075.51,
    "yearHigh": 14075.51,
    "yearLow": 13978.618,
    "marketCap": null,
    "priceAvg50": null,
    "priceAvg200": null,
    "volume": 0,
    "avgVolume": null,
    "exchange": "INDEX",
    "open": 14055.8,
    "previousClose": 14036.1,
    "eps": null,
    "pe": null,
    "earningsAnnouncement": null,
    "sharesOutstanding": null,
    "timestamp": 1605697056
  },
  {
    "symbol": "^AEX",
    "name": "AEX-INDEX",
    "price": 601.44,
    "changesPercentage": 0.08,
    "change": 0.5,
    "dayLow": 597.61,
    "dayHigh": 601.58,
    "yearHigh": 632.12,
    "yearLow": 389.6,
    "marketCap": null,
    "priceAvg50": 564.5161,
    "priceAvg200": 555.2021,
    "volume": 0,
    "avgVolume": 73746427,
    "exchange": "INDEX",
    "open": 598.36,
    "previousClose": 600.94,
    "eps": null,
    "pe": null,
    "earningsAnnouncement": null,
    "sharesOutstanding": null,
    "timestamp": 1605697056
  },
  {
    "symbol": "^MXX",
    "name": "IPC MEXICO",
    "price": 41948.79,
    "changesPercentage": 2.84,
    "change": 1156.98,
    "dayLow": 0,
    "dayHigh": 0,
    "yearHigh": 45955.41,
    "yearLow": 0,
    "marketCap": null,
    "priceAvg50": 38279.348,
    "priceAvg200": 37523.965,
    "volume": 0,
    "avgVolume": 165331493,
    "exchange": "INDEX",
    "open": 0,
    "previousClose": 40791.81,
    "eps": null,
    "pe": null,
    "earningsAnnouncement": null,
    "sharesOutstanding": null,
    "timestamp": 1605697056
  },
  {
    "symbol": "^GSPTSE",
    "name": "S&P/TSX Composite index",
    "price": 16948.06,
    "changesPercentage": 0.34,
    "change": 58.25,
    "dayLow": 16768.65,
    "dayHigh": 16952.78,
    "yearHigh": 17970.5,
    "yearLow": 11172.7,
    "marketCap": null,
    "priceAvg50": 16293.457,
    "priceAvg200": 15951.264,
    "volume": 264191798,
    "avgVolume": 228840264,
    "exchange": "INDEX",
    "open": 16800.19,
    "previousClose": 16889.81,
    "eps": null,
    "pe": null,
    "earningsAnnouncement": null,
    "sharesOutstanding": null,
    "timestamp": 1605697056
  },
  {
    "symbol": "^DJT",
    "name": "Dow Jones Transportation Averag",
    "price": 12434.97,
    "changesPercentage": 0.33,
    "change": 40.95,
    "dayLow": 12183.72,
    "dayHigh": 12461.65,
    "yearHigh": 12461.65,
    "yearLow": 6481.2,
    "marketCap": null,
    "priceAvg50": 11667.0625,
    "priceAvg200": 10321.825,
    "volume": 134814531,
    "avgVolume": 1535076,
    "exchange": "INDEX",
    "open": 12326.03,
    "previousClose": 12394.02,
    "eps": null,
    "pe": null,
    "earningsAnnouncement": null,
    "sharesOutstanding": null,
    "timestamp": 1605697056
  },
  {
    "symbol": "^IPSA",
    "name": "S&P/CLX IPSA",
    "price": 5058.88,
    "changesPercentage": 0,
    "change": 0,
    "dayLow": 5041.52,
    "dayHigh": 5072.83,
    "yearHigh": 5072.83,
    "yearLow": 5041.52,
    "marketCap": null,
    "priceAvg50": 5058.88,
    "priceAvg200": 5058.88,
    "volume": 0,
    "avgVolume": 0,
    "exchange": "INDEX",
    "open": 5071.76,
    "previousClose": 5058.88,
    "eps": null,
    "pe": null,
    "earningsAnnouncement": null,
    "sharesOutstanding": null,
    "timestamp": 1605697056
  },
  {
    "symbol": "TX60.TS",
    "name": "S&P/TSX 60 Index",
    "price": 1012.28,
    "changesPercentage": 0.44,
    "change": 4.42,
    "dayLow": 1000.52,
    "dayHigh": 1012.46,
    "yearHigh": 1012.46,
    "yearLow": 1000.52,
    "marketCap": null,
    "priceAvg50": null,
    "priceAvg200": null,
    "volume": 145162648,
    "avgVolume": null,
    "exchange": "INDEX",
    "open": 1002.55,
    "previousClose": 1007.86,
    "eps": null,
    "pe": null,
    "earningsAnnouncement": null,
    "sharesOutstanding": null,
    "timestamp": 1605697056
  },
  {
    "symbol": "^JN0U.JO",
    "name": "Top 40 USD Net TRI Index",
    "price": 3675.9,
    "changesPercentage": 0.82,
    "change": 29.93,
    "dayLow": 3636.51,
    "dayHigh": 3683,
    "yearHigh": 3977.41,
    "yearLow": 2036.53,
    "marketCap": null,
    "priceAvg50": 3356.819,
    "priceAvg200": 3197.424,
    "volume": 0,
    "avgVolume": 0,
    "exchange": "INDEX",
    "open": 3651.33,
    "previousClose": 3645.97,
    "eps": null,
    "pe": null,
    "earningsAnnouncement": null,
    "sharesOutstanding": null,
    "timestamp": 1605697056
  },
  {
    "symbol": "^NDX",
    "name": "NASDAQ 100",
    "price": 11977.489,
    "changesPercentage": -0.3,
    "change": -35.911,
    "dayLow": 11964.202,
    "dayHigh": 12047.131,
    "yearHigh": 12439.48,
    "yearLow": 6771.91,
    "marketCap": null,
    "priceAvg50": 11651.809,
    "priceAvg200": 10805.069,
    "volume": 636090188,
    "avgVolume": 3748333230,
    "exchange": "INDEX",
    "open": 12030.3,
    "previousClose": 12013.4,
    "eps": null,
    "pe": null,
    "earningsAnnouncement": null,
    "sharesOutstanding": null,
    "timestamp": 1605697056
  },
  {
    "symbol": "^CASE30",
    "name": "EGX 30 Price Return Index",
    "price": 11029,
    "changesPercentage": -0.32,
    "change": -35,
    "dayLow": 11028.6,
    "dayHigh": 11070,
    "yearHigh": 11070,
    "yearLow": 11028.6,
    "marketCap": null,
    "priceAvg50": null,
    "priceAvg200": null,
    "volume": 66875700,
    "avgVolume": null,
    "exchange": "INDEX",
    "open": 11064,
    "previousClose": 11064,
    "eps": null,
    "pe": null,
    "earningsAnnouncement": null,
    "sharesOutstanding": null,
    "timestamp": 1605697056
  },
  {
    "symbol": "^GSPC",
    "name": "S&P 500",
    "price": 3609.53,
    "changesPercentage": -0.48,
    "change": -17.38,
    "dayLow": 3588.68,
    "dayHigh": 3623.11,
    "yearHigh": 3645.99,
    "yearLow": 2191.86,
    "marketCap": null,
    "priceAvg50": 3446.6636,
    "priceAvg200": 3264.1353,
    "volume": 2404417306,
    "avgVolume": 4338874615,
    "exchange": "INDEX",
    "open": 3610.31,
    "previousClose": 3626.91,
    "eps": null,
    "pe": null,
    "earningsAnnouncement": null,
    "sharesOutstanding": null,
    "timestamp": 1605697056
  },
  {
    "symbol": "DX-Y.NYB",
    "name": "US Dollar/USDX - Index - Cash ",
    "price": 92.272,
    "changesPercentage": -0.16,
    "change": -0.144,
    "dayLow": 92.213,
    "dayHigh": 92.514,
    "yearHigh": 102.99,
    "yearLow": 91.75,
    "marketCap": null,
    "priceAvg50": 93.27111,
    "priceAvg200": 95.00677,
    "volume": null,
    "avgVolume": 0,
    "exchange": "INDEX",
    "open": 92.442,
    "previousClose": 92.416,
    "eps": null,
    "pe": null,
    "earningsAnnouncement": null,
    "sharesOutstanding": null,
    "timestamp": 1605697056
  },
  {
    "symbol": "^BUK100P",
    "name": "Cboe UK 100 Price Return",
    "price": 633.0503,
    "changesPercentage": -0.08,
    "change": -0.5301,
    "dayLow": 629.9785,
    "dayHigh": 633.5608,
    "yearHigh": 13029.66,
    "yearLow": 549.33,
    "marketCap": null,
    "priceAvg50": 591.11694,
    "priceAvg200": 3480.8591,
    "volume": 0,
    "avgVolume": 0,
    "exchange": "INDEX",
    "open": 633.4523,
    "previousClose": 633.5804,
    "eps": null,
    "pe": null,
    "earningsAnnouncement": null,
    "sharesOutstanding": null,
    "timestamp": 1605697056
  },
  {
    "symbol": "^AORD",
    "name": "ALL ORDINARIES",
    "price": 6726.5,
    "changesPercentage": 0.43,
    "change": 28.7,
    "dayLow": 6694.5,
    "dayHigh": 6738.3,
    "yearHigh": 7289.7,
    "yearLow": 4564.1,
    "marketCap": null,
    "priceAvg50": 6338.594,
    "priceAvg200": 6110.005,
    "volume": 0,
    "avgVolume": 1085490722,
    "exchange": "INDEX",
    "open": 6697.8,
    "previousClose": 6697.8,
    "eps": null,
    "pe": null,
    "earningsAnnouncement": null,
    "sharesOutstanding": null,
    "timestamp": 1605697056
  },
  {
    "symbol": "^RUT",
    "name": "Russell 2000",
    "price": 1791.9144,
    "changesPercentage": 0.37,
    "change": 6.578,
    "dayLow": 1755.3418,
    "dayHigh": 1795.888,
    "yearHigh": 1795.89,
    "yearLow": 966.22,
    "marketCap": null,
    "priceAvg50": 1629.1545,
    "priceAvg200": 1502.7196,
    "volume": 0,
    "avgVolume": 43447703,
    "exchange": "INDEX",
    "open": 1783.085,
    "previousClose": 1785.3364,
    "eps": null,
    "pe": null,
    "earningsAnnouncement": null,
    "sharesOutstanding": null,
    "timestamp": 1605697056
  },
  {
    "symbol": "^NSEI",
    "name": "NIFTY 50",
    "price": 12938.25,
    "changesPercentage": 0.5,
    "change": 64.05,
    "dayLow": 12819.35,
    "dayHigh": 12948.85,
    "yearHigh": 12948.85,
    "yearLow": 7511.1,
    "marketCap": null,
    "priceAvg50": 11911.542,
    "priceAvg200": 10909.8955,
    "volume": 0,
    "avgVolume": 611846,
    "exchange": "INDEX",
    "open": 12860.1,
    "previousClose": 12874.2,
    "eps": null,
    "pe": null,
    "earningsAnnouncement": null,
    "sharesOutstanding": null,
    "timestamp": 1605697056
  },
  {
    "symbol": "^JKSE",
    "name": "Jakarta Composite Index",
    "price": 5557.518,
    "changesPercentage": 0.5,
    "change": 27.578,
    "dayLow": 5530.876,
    "dayHigh": 5574.728,
    "yearHigh": 6348.526,
    "yearLow": 3911.716,
    "marketCap": null,
    "priceAvg50": 5162.3843,
    "priceAvg200": 5034.867,
    "volume": 0,
    "avgVolume": 104884554,
    "exchange": "INDEX",
    "open": 5530.876,
    "previousClose": 5529.94,
    "eps": null,
    "pe": null,
    "earningsAnnouncement": null,
    "sharesOutstanding": null,
    "timestamp": 1605697056
  },
  {
    "symbol": "RTSI.ME",
    "name": "RTS Index",
    "price": 1275.65,
    "changesPercentage": 1.37,
    "change": 17.19,
    "dayLow": 1253.23,
    "dayHigh": 1280.5,
    "yearHigh": 1280.5,
    "yearLow": 1253.23,
    "marketCap": null,
    "priceAvg50": null,
    "priceAvg200": null,
    "volume": 0,
    "avgVolume": null,
    "exchange": "INDEX",
    "open": 1258.77,
    "previousClose": 1258.46,
    "eps": null,
    "pe": null,
    "earningsAnnouncement": null,
    "sharesOutstanding": null,
    "timestamp": 1605697056
  },
  {
    "symbol": "^SP500TR",
    "name": "S&P 500 (TR)",
    "price": 7442.04,
    "changesPercentage": -0.46,
    "change": -34.75,
    "dayLow": 7399.21,
    "dayHigh": 7469.99,
    "yearHigh": 7511.31,
    "yearLow": 4466.72,
    "marketCap": null,
    "priceAvg50": 7097.613,
    "priceAvg200": 6700.386,
    "volume": 0,
    "avgVolume": 0,
    "exchange": "INDEX",
    "open": 7443.64,
    "previousClose": 7476.79,
    "eps": null,
    "pe": null,
    "earningsAnnouncement": null,
    "sharesOutstanding": null,
    "timestamp": 1605697056
  },
  {
    "symbol": "^VXN",
    "name": "CBOE NASDAQ 100 Voltility",
    "price": 27.31,
    "changesPercentage": -0.22,
    "change": -0.06,
    "dayLow": 0,
    "dayHigh": 0,
    "yearHigh": 84.67,
    "yearLow": 0,
    "marketCap": null,
    "priceAvg50": 34.60472,
    "priceAvg200": 32.809856,
    "volume": 0,
    "avgVolume": 0,
    "exchange": "INDEX",
    "open": 0,
    "previousClose": 27.37,
    "eps": null,
    "pe": null,
    "earningsAnnouncement": null,
    "sharesOutstanding": null,
    "timestamp": 1605697056
  },
  {
    "symbol": "^NSEBANK",
    "name": "NIFTY BANK",
    "price": 29749.85,
    "changesPercentage": 1.95,
    "change": 568.55,
    "dayLow": 29056.75,
    "dayHigh": 29784.75,
    "yearHigh": 32613.1,
    "yearLow": 16116.25,
    "marketCap": null,
    "priceAvg50": 24619.908,
    "priceAvg200": 22127.787,
    "volume": 0,
    "avgVolume": 3893,
    "exchange": "INDEX",
    "open": 29107.9,
    "previousClose": 29181.3,
    "eps": null,
    "pe": null,
    "earningsAnnouncement": null,
    "sharesOutstanding": null,
    "timestamp": 1605697056
  },
  {
    "symbol": "^XAX",
    "name": "NYSE AMEX COMPOSITE INDEX",
    "price": 2197.614,
    "changesPercentage": 0.82,
    "change": 17.877,
    "dayLow": 0,
    "dayHigh": 0,
    "yearHigh": 2636.9,
    "yearLow": 0,
    "marketCap": null,
    "priceAvg50": 2024.0083,
    "priceAvg200": 2019.7976,
    "volume": 0,
    "avgVolume": 0,
    "exchange": "INDEX",
    "open": 0,
    "previousClose": 2179.737,
    "eps": null,
    "pe": null,
    "earningsAnnouncement": null,
    "sharesOutstanding": null,
    "timestamp": 1605697056
  },
  {
    "symbol": "^VIX",
    "name": "CBOE Volatility Index",
    "price": 22.16,
    "changesPercentage": -1.29,
    "change": -0.29,
    "dayLow": 22.12,
    "dayHigh": 22.86,
    "yearHigh": 85.47,
    "yearLow": 11.42,
    "marketCap": null,
    "priceAvg50": 28.405277,
    "priceAvg200": 27.964748,
    "volume": 0,
    "avgVolume": 0,
    "exchange": "INDEX",
    "open": 22.86,
    "previousClose": 22.45,
    "eps": null,
    "pe": null,
    "earningsAnnouncement": null,
    "sharesOutstanding": null,
    "timestamp": 1605697056
  },
  {
    "symbol": "^DJI",
    "name": "Dow Jones Industrial Average",
    "price": 29783.35,
    "changesPercentage": -0.56,
    "change": -167.09,
    "dayLow": 29520.29,
    "dayHigh": 29872.42,
    "yearHigh": 29964.29,
    "yearLow": 18213.65,
    "marketCap": null,
    "priceAvg50": 28238.424,
    "priceAvg200": 26932.043,
    "volume": 376144655,
    "avgVolume": 415399846,
    "exchange": "INDEX",
    "open": 29800.15,
    "previousClose": 29950.44,
    "eps": null,
    "pe": null,
    "earningsAnnouncement": null,
    "sharesOutstanding": null,
    "timestamp": 1605697056
  },
  {
    "symbol": "IMOEX.ME",
    "name": "MOEX Russia Index",
    "price": 3062.92,
    "changesPercentage": 0.35,
    "change": 10.7,
    "dayLow": 3035.57,
    "dayHigh": 3072.91,
    "yearHigh": 3226.89,
    "yearLow": 2073.87,
    "marketCap": null,
    "priceAvg50": 2860.4277,
    "priceAvg200": 2848.616,
    "volume": 0,
    "avgVolume": 0,
    "exchange": "INDEX",
    "open": 3046.02,
    "previousClose": 3052.22,
    "eps": null,
    "pe": null,
    "earningsAnnouncement": null,
    "sharesOutstanding": null,
    "timestamp": 1605697056
  },
  {
    "symbol": "^STI",
    "name": "STI Index",
    "price": 2788.59,
    "changesPercentage": 0.36,
    "change": 10.04,
    "dayLow": 2774.78,
    "dayHigh": 2795.67,
    "yearHigh": 3283.89,
    "yearLow": 2208.42,
    "marketCap": null,
    "priceAvg50": 2548.8188,
    "priceAvg200": 2570.6252,
    "volume": 0,
    "avgVolume": 259508480,
    "exchange": "INDEX",
    "open": 2774.78,
    "previousClose": 2778.55,
    "eps": null,
    "pe": null,
    "earningsAnnouncement": null,
    "sharesOutstanding": null,
    "timestamp": 1605697056
  },
  {
    "symbol": "^BVSP",
    "name": "IBOVESPA",
    "price": 107248.63,
    "changesPercentage": 0.77,
    "change": 818.71,
    "dayLow": 0,
    "dayHigh": 0,
    "yearHigh": 119593,
    "yearLow": 0,
    "marketCap": null,
    "priceAvg50": 99237.586,
    "priceAvg200": 96619.055,
    "volume": 0,
    "avgVolume": 9505769,
    "exchange": "INDEX",
    "open": 0,
    "previousClose": 106429.92,
    "eps": null,
    "pe": null,
    "earningsAnnouncement": null,
    "sharesOutstanding": null,
    "timestamp": 1605697056
  },
  {
    "symbol": "^BFX",
    "name": "BEL 20",
    "price": 3601.78,
    "changesPercentage": 0.26,
    "change": 9.28,
    "dayLow": 3572.43,
    "dayHigh": 3602.09,
    "yearHigh": 4201.35,
    "yearLow": 2406.75,
    "marketCap": null,
    "priceAvg50": 3287.3535,
    "priceAvg200": 3307.8904,
    "volume": 0,
    "avgVolume": 17251340,
    "exchange": "INDEX",
    "open": 3580.59,
    "previousClose": 3592.5,
    "eps": null,
    "pe": null,
    "earningsAnnouncement": null,
    "sharesOutstanding": null,
    "timestamp": 1605697056
  },
  {
    "symbol": "^RVX",
    "name": "Cboe Russell 2000 Volatility Index",
    "price": 29.54,
    "changesPercentage": -1.83,
    "change": -0.55,
    "dayLow": 0,
    "dayHigh": 0,
    "yearHigh": 0,
    "yearLow": 0,
    "marketCap": null,
    "priceAvg50": null,
    "priceAvg200": null,
    "volume": 0,
    "avgVolume": null,
    "exchange": "INDEX",
    "open": 0,
    "previousClose": 30.09,
    "eps": null,
    "pe": null,
    "earningsAnnouncement": null,
    "sharesOutstanding": null,
    "timestamp": 1605697056
  },
  {
    "symbol": "^BSESN",
    "name": "S&P BSE SENSEX",
    "price": 44180.05,
    "changesPercentage": 0.52,
    "change": 227.34,
    "dayLow": 43785.78,
    "dayHigh": 44215.49,
    "yearHigh": 44215.49,
    "yearLow": 25638.9,
    "marketCap": null,
    "priceAvg50": 40563.676,
    "priceAvg200": 37045.324,
    "volume": 0,
    "avgVolume": 16800,
    "exchange": "INDEX",
    "open": 43978.58,
    "previousClose": 43952.71,
    "eps": null,
    "pe": null,
    "earningsAnnouncement": null,
    "sharesOutstanding": null,
    "timestamp": 1605697056
  },
  {
    "symbol": "^STOXX50E",
    "name": "ESTX 50 PR.EUR",
    "price": 3476.44,
    "changesPercentage": 0.23,
    "change": 7.96,
    "dayLow": 3451.89,
    "dayHigh": 3479.65,
    "yearHigh": 3867.28,
    "yearLow": 2302.84,
    "marketCap": null,
    "priceAvg50": 3227.4507,
    "priceAvg200": 3214.3152,
    "volume": 0,
    "avgVolume": 40122836,
    "exchange": "INDEX",
    "open": 3463.97,
    "previousClose": 3468.48,
    "eps": null,
    "pe": null,
    "earningsAnnouncement": null,
    "sharesOutstanding": null,
    "timestamp": 1605697056
  },
  {
    "symbol": "^MERV",
    "name": "MERVAL",
    "price": 38390.84,
    "changesPercentage": 0.61,
    "change": 233.89,
    "dayLow": 38156.95,
    "dayHigh": 39015.46,
    "yearHigh": 56114.04,
    "yearLow": 21738.62,
    "marketCap": null,
    "priceAvg50": 47523.89,
    "priceAvg200": 44713.84,
    "volume": 0,
    "avgVolume": 0,
    "exchange": "INDEX",
    "open": 38156.95,
    "previousClose": 38156.95,
    "eps": null,
    "pe": null,
    "earningsAnnouncement": null,
    "sharesOutstanding": null,
    "timestamp": 1605697056
  },
  {
    "symbol": "^DJITR",
    "name": "Dow Jones Industrial Average TR",
    "price": 68688.96,
    "changesPercentage": -0.53,
    "change": -365.67,
    "dayLow": 68085.71,
    "dayHigh": 69074.2,
    "yearHigh": 69074.2,
    "yearLow": 68085.71,
    "marketCap": null,
    "priceAvg50": null,
    "priceAvg200": null,
    "volume": 0,
    "avgVolume": null,
    "exchange": "INDEX",
    "open": 69074.2,
    "previousClose": 69054.63,
    "eps": null,
    "pe": null,
    "earningsAnnouncement": null,
    "sharesOutstanding": null,
    "timestamp": 1605697056
  },
  {
    "symbol": "^RUA",
    "name": "Russell 3000",
    "price": 2133.102,
    "changesPercentage": -0.25,
    "change": -5.4105,
    "dayLow": 2117.8726,
    "dayHigh": 2140.5325,
    "yearHigh": 2140.5325,
    "yearLow": 1259.73,
    "marketCap": null,
    "priceAvg50": 2028.62,
    "priceAvg200": 1910.6315,
    "volume": 0,
    "avgVolume": 163823,
    "exchange": "INDEX",
    "open": 2137.7659,
    "previousClose": 2138.5125,
    "eps": null,
    "pe": null,
    "earningsAnnouncement": null,
    "sharesOutstanding": null,
    "timestamp": 1605697056
  },
  {
    "symbol": "^RUTTR",
    "name": "Russell 2000 Total Return",
    "price": 9169.318,
    "changesPercentage": 0.37,
    "change": 33.846,
    "dayLow": 8982.178,
    "dayHigh": 9189.65,
    "yearHigh": 9189.65,
    "yearLow": 8982.178,
    "marketCap": null,
    "priceAvg50": null,
    "priceAvg200": null,
    "volume": 0,
    "avgVolume": null,
    "exchange": "INDEX",
    "open": 9124.139,
    "previousClose": 9135.472,
    "eps": null,
    "pe": null,
    "earningsAnnouncement": null,
    "sharesOutstanding": null,
    "timestamp": 1605697056
  },
  {
    "symbol": "^TYVIX",
    "name": "CBOE/CBOT 10-year U.S. Treasury",
    "price": 4.71,
    "changesPercentage": 0,
    "change": 0,
    "dayLow": 0,
    "dayHigh": 0,
    "yearHigh": 0,
    "yearLow": 0,
    "marketCap": null,
    "priceAvg50": null,
    "priceAvg200": null,
    "volume": 0,
    "avgVolume": null,
    "exchange": "INDEX",
    "open": 0,
    "previousClose": 4.71,
    "eps": null,
    "pe": null,
    "earningsAnnouncement": null,
    "sharesOutstanding": null,
    "timestamp": 1605697056
  }
]
